deep_speaker/__init__.py
deep_speaker/audio.py
deep_speaker/rescnn_model.py
speaker_verification/__init__.py
speaker_verification/__main__.py
speaker_verification/denoise.py
speaker_verification/model_evaluation.py
speaker_verification/sql_utils.py
speaker_verification/SQL/sqlite.db
speaker_verification/deep_speaker/__init__.py
speaker_verification/deep_speaker/audio.py
speaker_verification/deep_speaker/rescnn_model.py
speaker_verification/models/ResCNN_triplet_training_checkpoint_265.h5
speaker_verification-0.1.2.dist-info/LICENSE
speaker_verification-0.1.2.dist-info/METADATA
speaker_verification-0.1.2.dist-info/WHEEL
speaker_verification-0.1.2.dist-info/entry_points.txt
speaker_verification-0.1.2.dist-info/top_level.txt
speaker_verification-0.1.2.dist-info/zip-safe
speaker_verification-0.1.2.dist-info/RECORD
