Metadata-Version: 2.1
Name: speaker-verification
Version: 0.1.2
Summary: The machine learning package examines audio files submitted from a user
Home-page: https://github.com/OnTrack-UG-Squad/speaker-verification
Author-email: ajgriffi@deakin.edu.au
License: MIT
Project-URL: Bug Tracker, https://github.com/OnTrack-UG-Squad/speaker-verification/issues
Project-URL: Pull Requests, https://github.com/OnTrack-UG-Squad/speaker-verification/pulls
Platform: UNKNOWN
Classifier: Programming Language :: Python :: 3 :: Only
Classifier: Programming Language :: Python :: 3.8
Classifier: License :: OSI Approved :: MIT License
Classifier: Operating System :: OS Independent
Classifier: Topic :: Software Development :: Libraries
Classifier: Topic :: Utilities
Requires-Python: <3.9,>=3.8
Requires-Dist: audioread (==2.1.9)
Requires-Dist: Keras (==2.3.1)
Requires-Dist: librosa (==0.7.2)
Requires-Dist: numba (==0.48.0)
Requires-Dist: numpy (==1.18.5)
Requires-Dist: python-speech-features (==0.6)
Requires-Dist: tensorflow (>=2.1.0)
Requires-Dist: pytest
